Part 4/Other_modules.v
// Computer Architecture (CO224) - Lab 05 Part-3,4
// Design: Secondary parts (8 bit MUX, 32 bit MUX, Twos'complement, jump branch Adder, pc Adder, flowControl)
// Group: Group-49 
// Reg. No.: E/19/038 and E/19/256


// Module for Twos'complement
//The twosComp module returns the 2's complement value of the input as the output after a delay of 1 time unit
module twosComp(IN, OUT);

	input [7:0] IN;     // Input
	output [7:0] OUT;  // Output
	
	//Combinational logic to assign two's complement value of input to output after a delay of #1
	assign #1 OUT = ~IN + 1;

endmodule


//The Jump/Branch Adder calculates the target instruction address by adding the offset value to the PC+4 value
//after sign extension and multiplication by 4
//Contains a delay of 2 time units
module jumpbranchAdder(PC, OFFSET, TARGET);
	
	//Declaration of input and output ports
	input [31:0] PC;
	input [7:0] OFFSET;
	output [31:0] TARGET;
	
	wire [21:0] signBits;		//Bus to store extended sign bits
	
	assign signBits = {22{OFFSET[7]}};	//assigning the sign bit (MSB) of OFFSET to all 22 bits in signBits
	
	//GENERATING TARGET address by adding the OFFSET * 4 to the PC value after a delay of 2 time units
	//First 22 bits contain the extended sign bits, next 8 bits contain the actual offset, the next two bits are zeros due to shifting left by 2 (multiplication by 4)
	assign #2 TARGET = PC + {signBits, OFFSET, 2'b0};	
	
endmodule


//The pcAdder module generates the PC+4 value from the PC input after a delay of 1 time unit
module pcAdder(PC, PCplus4);
	
	//Declaration of input and output ports
	input [31:0] PC;
	output [31:0] PCplus4;

	//Assign PC+4 value to the output after 1 time unit delay
	assign #1 PCplus4 = PC + 4;
	
endmodule


// Module for MUX unit
//Generic MUX module to be used inside the CPU
//Operation: SELECT == 0 : OUT = IN1
//			 SELECT == 1 : OUT = IN2
//Does not contain delays
module mux(IN1, IN2, SELECT, OUT);

	//Input and output port declaration
	input [7:0] IN1;       // Input DATA
	input [7:0] IN2;       // Input DATA
	input SELECT;          // Input port for SELECT
	output reg [7:0] OUT;  // Output DATA
	
	//MUX should update output value upon change of any of the inputs
	always @ (IN1, IN2, SELECT)
	begin
		if (SELECT == 1'b1)		//If SELECT is HIGH, switch to 2nd input
		begin
			OUT = IN2;
		end
		else					//If SELECT is LOW, switch to 1st input
		begin
			OUT = IN1;
		end
	end

endmodule


//32-bit MUX module for flow control operations
//Operation: SELECT == 0 : OUT = IN1
//			 SELECT == 1 : OUT = IN2
//Does not contain delays
module mux32(IN1, IN2, SELECT, OUT);

	//Input and output port declaration
	input [31:0] IN1, IN2;
	input SELECT;
	output reg [31:0] OUT;
	
	//MUX should update output value upon change of any of the inputs
	always @ (IN1, IN2, SELECT)
	begin
		if (SELECT == 1'b1)		//If SELECT is HIGH, switch to 2nd input
		begin
			OUT = IN2;
		end
		else					//If SELECT is LOW, switch to 1st input
		begin
			OUT = IN1;
		end
	end

endmodule


//Combinational Control Unit for flow control operations
//Operation: JUMP = 0  BRANCH = 0          : OUT = 0 (Normal flow)
//			 JUMP = 1                      : OUT = 1 (Offset flow)
//			 JUMP = 0  BRANCH = 1 ZERO = 0 : OUT = 0 (Normal flow)
//			 JUMP = 0  BRANCH = 1 ZERO = 1 : OUT = 1 (Offset flow)
//Contains no delays
module flowControl(JUMP, BRANCH, ZERO, OUT);

	//Input and output port declaration
	input JUMP, BRANCH, ZERO;
	output OUT;
	
	//Assigns OUT based on values of JUMP, BRANCH and ZERO using simple combinational logic
	assign OUT = JUMP | (BRANCH & ZERO);

endmodule

Part 4/or.v
// Computer Architecture (CO224) - Lab 05 Part-1
// Design: OR module
// Group: Group-49 
// Reg. No.: E/19/038 and E/19/256


// Module for OR unit
module OR(DATA1, DATA2, RESULT);

	input [7:0] DATA1;    // Input data 1 for addition
    input [7:0] DATA2;    // Input data 2 for addition
	output [7:0] RESULT;  // Output result for addition
	
	//Assigns logical OR result of DATA1 and DATA2 to RESULT after 1 time unit delay
	assign #1 RESULT = DATA1 | DATA2;
	
endmodule

Part 3/and.v
// Computer Architecture (CO224) - Lab 05 Part-1
// Design: AND module
// Group: Group-49 
// Reg. No.: E/19/038 and E/19/256


// Module for AND unit
module AND(DATA1, DATA2, RESULT);

	input [7:0] DATA1;    // Input data 1 for addition
    input [7:0] DATA2;    // Input data 2 for addition
	output [7:0] RESULT;  // Output result for addition
	
	//Assigns logical AND result of DATA1 and DATA2 to RESULT after 1 time unit delay
	assign #1 RESULT = DATA1 & DATA2;
	
endmodule

Part 4/add.v
// Computer Architecture (CO224) - Lab 05 Part-1
// Design: ADD module
// Group: Group-49 
// Reg. No.: E/19/038 and E/19/256


// Module for ADD unit
module ADD(DATA1, DATA2, RESULT);

	input [7:0] DATA1;    // Input data 1 for addition
    input [7:0] DATA2;    // Input data 2 for addition
	output [7:0] RESULT;  // Output result for addition
	
	//Assigns evaluated addition of DATA1 and DATA2 to RESULT after 2 time unit delay
	assign #2 RESULT = DATA1 + DATA2;
	
endmodule

Part 3/forward.v
// Computer Architecture (CO224) - Lab 05 Part-1
// Design: FORWARD module
// Group: Group-49 
// Reg. No.: E/19/038 and E/19/256


// Module for FORWARD unit
module FORWARD(DATA, RESULT);

	input [7:0] DATA;    // Input data for addition
	output [7:0] RESULT;  // Output result for addition
	
	//Assigns the value of DATA to RESULT after a delay of 1 time unit
	assign #1 RESULT = DATA;

endmodule

Data Memory/Lab6 Part3/alu.v
// Computer Architecture (CO224) - Lab 05 Part-1
// Design: ALU of Simple Processor
// Group: Group-49 
// Reg. No.: E/19/038 and E/19/256
`include "add.v"
`include"forward.v"
`include "and.v"
`include "or.v"
`timescale 1ns/100ps

// Module for ALU
module alu(DATA1, DATA2, RESULT, SELECT, ZERO);
	
	input [7:0] DATA1;       // Input port for DATA1, an 8-bit vector.
    input [7:0] DATA2;       // Input port for DATA2, an 8-bit vector.
    input [2:0] SELECT;      // Input port for SELECT, a 3-bit vector.
    output reg [7:0] RESULT; // Output port for RESULT, an 8-bit vector.
	output ZERO;             // Output port for ZERO
	
    // Internal signals for functional units
	wire [7:0] forwardOut; // Internal register to hold the result for the FORWARD operation.
	wire [7:0] addOut;     // Internal register to hold the result for the ADD operation.
	wire [7:0] andOut;     // Internal register to hold the result for the AND operation.
	wire [7:0] orOut;      // Internal register to hold the result for the OR operation.
	
	
	// Instantiation of functional unit modules
	FORWARD forwardUnit(DATA2, forwardOut); // Instantiate FORWARD unit
	ADD addUnit(DATA1, DATA2, addOut);      // Instantiate ADD unit
	AND andUnit(DATA1, DATA2, andOut);      // Instantiate AND unit
	OR orUnit(DATA1, DATA2, orOut);         // Instantiate OR unit
	
	
    // Output selection using a MUX
	//One of the functional units' results is sent to the RESULT output based on the SELECT value
	always @* //(forwardOut, addOut, andOut, orOut, SELECT)	
	begin
		case (SELECT)
			3'b000 :	RESULT = forwardOut;	// If SELECT is 000, output forward_result.
			3'b001 :	RESULT = addOut;		// If SELECT is 001, output add_result.
			3'b010 :	RESULT = andOut;		// If SELECT is 010, output and_result.
			3'b011 :	RESULT = orOut;			// If SELECT is 011, output or_result.
			
		endcase
	end

	//This section of the ALU contains the combinational logic to generate the ZERO output
	assign ZERO = ~(RESULT[0] | RESULT[1] | RESULT[2] | RESULT[3] | RESULT[4] | RESULT[5] | RESULT[6] | RESULT[7]);

		
endmodule

Part 5/reg_file.v
// Computer Architecture (CO224) - Lab 05 Part-2
// Design: Register File of Simple Processor
// Group: Group-49 
// Reg. No.: E/19/038 and E/19/256

module reg_file(IN,OUT1,OUT2,INADDRESS,OUT1ADDRESS,OUT2ADDRESS, WRITE, CLK, RESET);

	input[7:0] IN;                // Input data
    output [7:0] OUT1;            // Output data 1
    output [7:0] OUT2;            // Output data 2
    input[2:0] INADDRESS;         // Input address 
    input[2:0] OUT1ADDRESS;       // Output 1 address 
    input[2:0] OUT2ADDRESS;       // Output 2 address 
    input WRITE;                  // Write control signal
    input CLK;                    // Clock signal
    input RESET;                  // Reset control signal
	
    // Declaration of register file by using 8 element array of 8 bit registers
	reg [7:0] REGISTER [7:0];

	//Iterator variable used in for loop
	integer i;
	
	// These assign statements are executed asynchronously (data transmitted concurrently).
    // There are artificial delays of two time units for register reading.
	assign #2 OUT1 = REGISTER[OUT1ADDRESS];		// Assigning output 1 from register file
	assign #2 OUT2 = REGISTER[OUT2ADDRESS];		// Assigning output 2 from register file
	
	
	// This block is works in synchronous manner 
    // this is work during the rising edge of the clock pulse.
	always @ (posedge CLK)
	begin
		if (RESET == 1'b1)		//If the RESET signal is HIGH, registers must be cleared
		begin
		
			#1 // Artificial delay of one time unit for resetting
            for (i = 0; i < 8; i = i + 1)			//For loop to iterate over all 8 register addresses after 1 time unit delay
			begin
				REGISTER[i] = 8'b00000000;		//Setting each element of the REGISTER array to 0
			end
			
		end
		else if (WRITE == 1'b1)			// The else condition handles data transfer when WRITE is high.
                                        // It transfers data from the input IN to the register specified by the address INADDRESS.
		begin
			#1 // Artificial delays of one time units for register writing
            REGISTER[INADDRESS] = IN;		//Assigns the input value IN to relevant register address 
		end
	end
	
	initial begin
			$monitor($time, "\t%d\t%d", OUT1,OUT2);
		end
	

endmodule

Part 4/cpu.v
// Computer Architecture (CO224) - Lab 05 Part-4
// Design: CPU of Simple Processor
// Group: Group-49 
// Reg. No.: E/19/038 and E/19/256

`include "alu.v"
`include "reg_file.v"
`include "Other_modules.v"

//The CPU module contains all the necessary components of the CPU
//The various sub-modules of the CPU are instantiated within the module
//The control logic for the operation of the CPU exists within this top module
module cpu(PC, INSTRUCTION, CLK, RESET);

    input [31:0] INSTRUCTION;     // Input Instruction
    input CLK;                    // Clock signal
    input RESET;                  // Reset control signal
    
    output reg [31:0] PC;         // Output PC
    
    wire [2:0] READREG1;          // Read register 1 address
    wire [2:0] READREG2;          // Read register 2 address
    wire [2:0] WRITEREG;          // Write register address
    wire [7:0] REGOUT1;           // Data from register 1
    wire [7:0] REGOUT2;           // Data from register 2
    reg WRITEENABLE;              // Write enable control
    
    wire [7:0] OPERAND1;          // Operand 1 for ALU
    wire [7:0] OPERAND2;          // Operand 2 for ALU
    wire [7:0] ALURESULT;         // Result from ALU
    reg [2:0] ALUOP;              // ALU operation control
	wire zero;                    // ZERO operand for ALU
    
    wire [7:0] negatedOp;         // Negated operand for MUX
    wire [7:0] registerOp;        // Operand from register for MUX
    reg signSelect;               // Sign selection control
    
    wire [7:0] IMMEDIATE;         // Immediate value
    reg immSelect;                // Immediate selection control
    
	wire [31:0] PCplus4;          // PC+4 value updated
	wire [31:0] PCout;            // PC value updated 

	wire [31:0] TARGET;           // TRAGET operand for jump/branch adder 
	wire [7:0] OFFSET;            // OFFSET operand for jump/branch adder
	
	//Connections for flow control combinational unit
	reg JUMP;
	reg BRANCH;

	wire flowSelect;              // Flow contral MUX
    
    reg [7:0] OPCODE;             // Opcode

	
	//Instantiation of CPU modules
	reg_file my_reg(ALURESULT, REGOUT1, REGOUT2, WRITEREG, READREG1, READREG2, WRITEENABLE, CLK, RESET);
	alu my_alu(REGOUT1, OPERAND2, ALURESULT, ALUOP, ZERO);
	twosComp my_twosComp(REGOUT2, negatedOp);
	mux negationMUX(REGOUT2, negatedOp, signSelect, registerOp);
	mux immediateMUX(registerOp, IMMEDIATE, immSelect, OPERAND2);

	pcAdder my_pcAdder(PC, PCplus4);
	jumpbranchAdder my_jumpbranchAdder(PCplus4, OFFSET, TARGET);
	flowControl my_flowControl(JUMP, BRANCH, ZERO, flowSelect);
	mux32 flowctrlmux(PCplus4, TARGET, flowSelect, PCout);

	// Control Logic for CPU
	
	//PC Update (Fetching Mechanism)
	always @ ( posedge CLK)
	begin
		if (RESET == 1'b1) 
		begin
			#1
			PC = 0;		//If RESET signal is HIGH, set PC to zero
		end
		else #1 PC = PCout;		//Else, write new PC value
	end
	
	
	//Relevant portions of INSTRUCTION are mapped to the respective units
	
	///////////////////////////////////////////////////////////////////
	/*    OP-CODE    /      RD       /       RT      /     RS/IMM    */
	/*    [31:24]    /    [23:16]    /     [15:8]    /      [7:0]    */
	///////////////////////////////////////////////////////////////////
	/*       |       /        |      /        |      /       |       */
	/*    OPCODE     /    WRITEREG   /    READREG1   /    READREG2   */
	/*               /               /               /   IMMEDIATE   */
	/*****************************************************************/
	assign READREG1 = INSTRUCTION[15:8];
	assign IMMEDIATE = INSTRUCTION[7:0];
	assign READREG2 = INSTRUCTION[7:0];
	assign WRITEREG = INSTRUCTION[23:16];
	assign OFFSET = INSTRUCTION[23:16];
	
	//Decoding the instruction
	always @ (INSTRUCTION)
	begin
	
		OPCODE = INSTRUCTION[31:24];	//Mapping the OP-CODE section of the instruction to OPCODE
		
		#1	//1 Time Unit Delay for Decoding process
		
		case (OPCODE)
		
			//loadi instruction
			8'b00000000:	begin
								ALUOP = 3'b000;			//Set ALU to forward
								immSelect = 1'b1;		//Set MUX to select immediate value
								signSelect = 1'b0;		//Set sign select MUX to positive sign
								JUMP = 1'b0;			//Set JUMP control signal to zero
								BRANCH = 1'b0;			//Set BRANCH control signal to zero
								WRITEENABLE = 1'b1;		//Enable writing to register
							end
		
			//mov instruction
			8'b00000001:	begin
								ALUOP = 3'b000;			//Set ALU to FORWARD
								immSelect = 1'b0;		//Set MUX to select register input
								signSelect = 1'b0;		//Set sign select MUX to positive sign
								JUMP = 1'b0;			//Set JUMP control signal to zero
								BRANCH = 1'b0;			//Set BRANCH control signal to zero
								WRITEENABLE = 1'b1;		//Enable writing to register
							end
			
			//add instruction
			8'b00000010:	begin
								ALUOP = 3'b001;			//Set ALU to ADD
								immSelect = 1'b0;		//Set MUX to select register input
								signSelect = 1'b0;		//Set sign select MUX to positive sign
								JUMP = 1'b0;			//Set JUMP control signal to zero
								BRANCH = 1'b0;			//Set BRANCH control signal to zero
								WRITEENABLE = 1'b1;		//Enable writing to register
							end	
		
			//sub instruction
			8'b00000011:	begin
								ALUOP = 3'b001;			//Set ALU to ADD
								immSelect = 1'b0;		//Set MUX to select register input
								signSelect = 1'b1;		//Set sign select MUX to negative sign
								JUMP = 1'b0;			//Set JUMP control signal to zero
								BRANCH = 1'b0;			//Set BRANCH control signal to zero
								WRITEENABLE = 1'b1;		//Enable writing to register
							end

			//and instruction
			8'b00000100:	begin
								ALUOP = 3'b010;			//Set ALU to AND
								immSelect = 1'b0;		//Set MUX to select register input
								signSelect = 1'b0;		//Set sign select MUX to positive sign
								JUMP = 1'b0;			//Set JUMP control signal to zero
								BRANCH = 1'b0;			//Set BRANCH control signal to zero
								WRITEENABLE = 1'b1;		//Enable writing to register
							end
							
			//or operation
			8'b00000101:	begin
								ALUOP = 3'b011;			//Set ALU to OR
								immSelect = 1'b0;		//Set MUX to select register input
								signSelect = 1'b0;		//Set sign select MUX to positive sign
								JUMP = 1'b0;			//Set JUMP control signal to zero
								BRANCH = 1'b0;			//Set BRANCH control signal to zero
								WRITEENABLE = 1'b1;		//Enable writing to register
							end

			//j instruction
			8'b00000110:	begin
								JUMP = 1'b1;			//Set JUMP control signal to 1
								BRANCH = 1'b0;			//Set BRANCH control signal to zero
								WRITEENABLE = 1'b0;		//Disable writing to register
							end
			
			//beq instruction
			8'b00000111:	begin
								ALUOP = 3'b001;			//Set ALU to ADD
								immSelect = 1'b0;		//Set MUX to select register input
								signSelect = 1'b1;		//Set sign select MUX to negative sign
								JUMP = 1'b0;			//Set JUMP control signal to zero
								BRANCH = 1'b1;			//Set BRANCH control signal to 1
								WRITEENABLE = 1'b0;		//Enable writing to register
							end

		endcase
		
	end
	
endmodule

Part 4/cpu_tb.v
// Computer Architecture (CO224) - Lab 05
// Design: Testbench of Integrated CPU of Simple Processor
// Author: Kisaru Liyanage
`include "cpu.v"

module cpu_tb;

    reg CLK, RESET;
    wire [31:0] PC;
    wire [31:0] INSTRUCTION;
    integer i;
    
    /* 
    ------------------------
     SIMPLE INSTRUCTION MEM
    ------------------------
    */
    
    // TODO: Initialize an array of registers (8x1024) named 'instr_mem' to be used as instruction memory
	reg [7:0] instr_mem [1023:0];
    
    // TODO: Create combinational logic to support CPU instruction fetching, given the Program Counter(PC) value 
    //       (make sure you include the delay for instruction fetching here)
	assign #2 INSTRUCTION = {instr_mem[PC+3], instr_mem[PC+2], instr_mem[PC+1], instr_mem[PC]};
    
    initial
    begin
        // Initialize instruction memory with the set of instructions you need execute on CPU
        
        // METHOD 1: manually loading instructions to instr_mem
        //{instr_mem[10'd3], instr_mem[10'd2], instr_mem[10'd1], instr_mem[10'd0]} = 32'b00000000000001000000000000000101;
        //{instr_mem[10'd7], instr_mem[10'd6], instr_mem[10'd5], instr_mem[10'd4]} = 32'b00000000000000100000000000001001;
        //{instr_mem[10'd11], instr_mem[10'd10], instr_mem[10'd9], instr_mem[10'd8]} = 32'b00000010000001100000010000000010;
        
        // METHOD 2: loading instr_mem content from instr_mem.mem file
        $readmemb("instr_mem.mem", instr_mem);
    end
    
    /* 
    -----
     CPU
    -----
    */
    cpu mycpu(PC, INSTRUCTION, CLK, RESET);

/* START DEBUGGING CODE*/
    initial 
    begin 
    // monitor changes in reg file content and print (used to check whether the CPU is running properly)
    #5;
    $display("\n\t\t\t==================================================");
    $display("\t\t\t Change of register Content Starting from Time #5");
    $display("\t\t\t==================================================\n");
    $display("\t\ttime\treg0\treg1\treg2\treg3\treg4\treg5\treg6\treg7");
    $display("\t\t----------------------------------------------------------------------");
    $monitor($time, "\t%d\t%d\t%d\t%d\t%d\t%d\t%d\t%d", mycpu.my_reg.REGISTER[0], mycpu.my_reg.REGISTER[1], mycpu.my_reg.REGISTER[2], mycpu.my_reg.REGISTER[3], mycpu.my_reg.REGISTER[4], mycpu.my_reg.REGISTER[5], mycpu.my_reg.REGISTER[6], mycpu.my_reg.REGISTER[7]);
    end


    initial
    begin
        // generate files needed to plot the waveform using GTKWave
        $dumpfile("cpu_wavedata_new.vcd");
		$dumpvars(0, cpu_tb);
        for (i=0; i<8; i++)
            $dumpvars(1, mycpu.my_reg.REGISTER[i]);
        
        CLK = 1'b0;
		RESET = 1'b1;
        
        // TODO: Reset the CPU (by giving a pulse to RESET signal) to start the program execution
		#5
		RESET = 1'b0;
        
        // finish simulation after some time
        #300
        $finish;
        
    end
    
    // clock signal generation
    always
        #4 CLK = ~CLK;
        

endmodule

Part 4/cpu_wavedata_new.vcd
$date
	Wed May 22 22:14:29 2024
$end
$version
	Icarus Verilog
$end
$timescale
	1s
$end
$scope module cpu_tb $end
$var wire 32 ! PC [31:0] $end
$var wire 32 " INSTRUCTION [31:0] $end
$var reg 1 # CLK $end
$var reg 1 $ RESET $end
$var integer 32 % i [31:0] $end
$scope module mycpu $end
$var wire 1 # CLK $end
$var wire 32 & INSTRUCTION [31:0] $end
$var wire 1 $ RESET $end
$var wire 8 ' registerOp [7:0] $end
$var wire 8 ( negatedOp [7:0] $end
$var wire 1 ) flowSelect $end
$var wire 1 * ZERO $end
$var wire 3 + WRITEREG [2:0] $end
$var wire 32 , TARGET [31:0] $end
$var wire 8 - REGOUT2 [7:0] $end
$var wire 8 . REGOUT1 [7:0] $end
$var wire 3 / READREG2 [2:0] $end
$var wire 3 0 READREG1 [2:0] $end
$var wire 32 1 PCplus4 [31:0] $end
$var wire 32 2 PCout [31:0] $end
$var wire 8 3 OPERAND2 [7:0] $end
$var wire 8 4 OFFSET [7:0] $end
$var wire 8 5 IMMEDIATE [7:0] $end
$var wire 8 6 ALURESULT [7:0] $end
$var reg 3 7 ALUOP [2:0] $end
$var reg 1 8 BRANCH $end
$var reg 1 9 JUMP $end
$var reg 8 : OPCODE [7:0] $end
$var reg 32 ; PC [31:0] $end
$var reg 1 < WRITEENABLE $end
$var reg 1 = immSelect $end
$var reg 1 > signSelect $end
$scope module flowctrlmux $end
$var wire 1 ) SELECT $end
$var wire 32 ? IN2 [31:0] $end
$var wire 32 @ IN1 [31:0] $end
$var reg 32 A OUT [31:0] $end
$upscope $end
$scope module immediateMUX $end
$var wire 8 B IN2 [7:0] $end
$var wire 1 = SELECT $end
$var wire 8 C IN1 [7:0] $end
$var reg 8 D OUT [7:0] $end
$upscope $end
$scope module my_alu $end
$var wire 8 E DATA2 [7:0] $end
$var wire 3 F SELECT [2:0] $end
$var wire 1 * ZERO $end
$var wire 8 G orOut [7:0] $end
$var wire 8 H forwardOut [7:0] $end
$var wire 8 I andOut [7:0] $end
$var wire 8 J addOut [7:0] $end
$var wire 8 K DATA1 [7:0] $end
$var reg 8 L RESULT [7:0] $end
$scope module addUnit $end
$var wire 8 M DATA2 [7:0] $end
$var wire 8 N RESULT [7:0] $end
$var wire 8 O DATA1 [7:0] $end
$upscope $end
$scope module andUnit $end
$var wire 8 P DATA2 [7:0] $end
$var wire 8 Q RESULT [7:0] $end
$var wire 8 R DATA1 [7:0] $end
$upscope $end
$scope module forwardUnit $end
$var wire 8 S DATA [7:0] $end
$var wire 8 T RESULT [7:0] $end
$upscope $end
$scope module orUnit $end
$var wire 8 U DATA2 [7:0] $end
$var wire 8 V RESULT [7:0] $end
$var wire 8 W DATA1 [7:0] $end
$upscope $end
$upscope $end
$scope module my_flowControl $end
$var wire 1 8 BRANCH $end
$var wire 1 9 JUMP $end
$var wire 1 ) OUT $end
$var wire 1 * ZERO $end
$upscope $end
$scope module my_jumpbranchAdder $end
$var wire 8 X OFFSET [7:0] $end
$var wire 22 Y signBits [21:0] $end
$var wire 32 Z TARGET [31:0] $end
$var wire 32 [ PC [31:0] $end
$upscope $end
$scope module my_pcAdder $end
$var wire 32 \ PC [31:0] $end
$var wire 32 ] PCplus4 [31:0] $end
$upscope $end
$scope module my_reg $end
$var wire 1 # CLK $end
$var wire 8 ^ IN [7:0] $end
$var wire 3 _ INADDRESS [2:0] $end
$var wire 8 ` OUT1 [7:0] $end
$var wire 3 a OUT1ADDRESS [2:0] $end
$var wire 8 b OUT2 [7:0] $end
$var wire 3 c OUT2ADDRESS [2:0] $end
$var wire 1 $ RESET $end
$var wire 1 < WRITE $end
$var integer 32 d i [31:0] $end
$upscope $end
$scope module my_twosComp $end
$var wire 8 e IN [7:0] $end
$var wire 8 f OUT [7:0] $end
$upscope $end
$scope module negationMUX $end
$var wire 8 g IN1 [7:0] $end
$var wire 8 h IN2 [7:0] $end
$var wire 1 > SELECT $end
$var reg 8 i OUT [7:0] $end
$upscope $end
$upscope $end
$upscope $end
$scope module cpu_tb $end
$scope module mycpu $end
$scope module my_reg $end
$var reg 8 j \REGISTER[0] [7:0] $end
$upscope $end
$upscope $end
$upscope $end
$scope module cpu_tb $end
$scope module mycpu $end
$scope module my_reg $end
$var reg 8 k \REGISTER[1] [7:0] $end
$upscope $end
$upscope $end
$upscope $end
$scope module cpu_tb $end
$scope module mycpu $end
$scope module my_reg $end
$var reg 8 l \REGISTER[2] [7:0] $end
$upscope $end
$upscope $end
$upscope $end
$scope module cpu_tb $end
$scope module mycpu $end
$scope module my_reg $end
$var reg 8 m \REGISTER[3] [7:0] $end
$upscope $end
$upscope $end
$upscope $end
$scope module cpu_tb $end
$scope module mycpu $end
$scope module my_reg $end
$var reg 8 n \REGISTER[4] [7:0] $end
$upscope $end
$upscope $end
$upscope $end
$scope module cpu_tb $end
$scope module mycpu $end
$scope module my_reg $end
$var reg 8 o \REGISTER[5] [7:0] $end
$upscope $end
$upscope $end
$upscope $end
$scope module cpu_tb $end
$scope module mycpu $end
$scope module my_reg $end
$var reg 8 p \REGISTER[6] [7:0] $end
$upscope $end
$upscope $end
$upscope $end
$scope module cpu_tb $end
$scope module mycpu $end
$scope module my_reg $end
$var reg 8 q \REGISTER[7] [7:0] $end
$upscope $end
$upscope $end
$upscope $end
$enddefinitions $end
$comment Show the parameter values. $end
$dumpall
$end
#0
$dumpvars
bx q
bx p
bx o
bx n
bx m
bx l
bx k
bx j
bx i
bx h
bx g
bx f
bx e
bx d
bx c
bx b
bx a
bx `
bx _
bx ^
bx ]
bx \
bx [
bx Z
bx Y
bx X
bx W
bx V
bx U
bx T
bx S
bx R
bx Q
bx P
bx O
bx N
bx M
bx L
bx K
bx J
bx I
bx H
bx G
bx F
bx E
bx D
bx C
bx B
bx A
bx @
bx ?
x>
x=
x<
bx ;
bx :
x9
x8
bx 7
bx 6
bx 5
bx 4
bx 3
bx 2
bx 1
bx 0
bx /
bx .
bx -
bx ,
bx +
x*
x)
bx (
bx '
bx &
b1000 %
1$
0#
bx "
bx !
$end
#4
1#
#5
b0 q
b0 p
b0 o
b0 n
b0 m
b0 l
b0 k
b0 j
b1000 d
b0 !
b0 ;
b0 \
0$
#6
b100 2
b100 A
b100 1
b100 @
b100 [
b100 ]
#7
b0 0
b0 a
b10 /
b10 c
b100 +
b100 _
b0 Y
b0 :
b1010 5
b1010 B
b100 4
b100 X
b1000000000000001010 "
b1000000000000001010 &
#8
0)
b1010 3
b1010 D
b1010 E
b1010 M
b1010 P
b1010 S
b1010 U
1<
08
09
0>
1=
b0 7
b0 F
0#
#9
0*
b1010 6
b1010 L
b1010 ^
b0 '
b0 C
b0 i
b0x0x0 I
b0x0x0 Q
bx1x1x G
bx1x1x V
b1010 H
b1010 T
b0 .
b0 K
b0 O
b0 R
b0 W
b0 `
b0 -
b0 b
b0 e
b0 g
b10100 ,
b10100 ?
b10100 Z
#10
b1010 G
b1010 V
b0 I
b0 Q
b0 (
b0 f
b0 h
#11
b1010 J
b1010 N
#12
1#
#13
b100 !
b100 ;
b100 \
b1010 n
#14
b1000 2
b1000 A
b1000 1
b1000 @
b1000 [
b1000 ]
#15
b1 3
b1 D
b1 E
b1 M
b1 P
b1 S
b1 U
b1 /
b1 c
b101 +
b101 _
b1 5
b1 B
b101 4
b101 X
b1010000000000000001 "
b1010000000000000001 &
#16
b1 6
b1 L
b1 ^
b1 G
b1 V
b1 H
b1 T
0#
#17
b1 J
b1 N
b11100 ,
b11100 ?
b11100 Z
#20
1#
#21
b1 o
b1000 !
b1000 ;
b1000 \
#22
b1100 2
b1100 A
b1100 1
b1100 @
b1100 [
b1100 ]
#23
b110 +
b110 _
b110 4
b110 X
b1100000000000000001 "
b1100000000000000001 &
#24
0#
#25
b100100 ,
b100100 ?
b100100 Z
#28
1#
#29
b1100 !
b1100 ;
b1100 \
b1 p
#30
b10000 2
b10000 A
b10000 1
b10000 @
b10000 [
b10000 ]
#31
b1001 3
b1001 D
b1001 E
b1001 M
b1001 P
b1001 S
b1001 U
b111 +
b111 _
b1001 5
b1001 B
b111 4
b111 X
b1110000000000001001 "
b1110000000000001001 &
#32
b1001 6
b1001 L
b1001 ^
b1001 G
b1001 V
b1001 H
b1001 T
0#
#33
b1001 J
b1001 N
b101100 ,
b101100 ?
b101100 Z
#36
1#
#37
b1001 q
b10000 !
b10000 ;
b10000 \
#38
b10100 2
b10100 A
b10100 1
b10100 @
b10100 [
b10100 ]
#39
b100 0
b100 a
b101 3
b101 D
b101 E
b101 M
b101 P
b101 S
b101 U
b101 /
b101 c
b100 +
b100 _
b11 :
b101 5
b101 B
b100 4
b100 X
b11000001000000010000000101 "
b11000001000000010000000101 &
#40
b0 3
b0 D
b0 E
b0 M
b0 P
b0 S
b0 U
b101 G
b101 V
b101 H
b101 T
1>
0=
b1 7
b1 F
0#
#41
b0 G
b0 V
b0 H
b0 T
b1010 .
b1010 K
b1010 O
b1010 R
b1010 W
b1010 `
b1 -
b1 b
b1 e
b1 g
b100100 ,
b100100 ?
b100100 Z
#42
b11111111 3
b11111111 D
b11111111 E
b11111111 M
b11111111 P
b11111111 S
b11111111 U
b11111111 '
b11111111 C
b11111111 i
b1010 G
b1010 V
b11111111 (
b11111111 f
b11111111 h
#43
b1010 I
b1010 Q
b11111111 G
b11111111 V
b11111111 H
b11111111 T
#44
1#
#45
b10100 !
b10100 ;
b10100 \
b1001 n
#46
b11000 2
b11000 A
b11000 1
b11000 @
b11000 [
b11000 ]
#47
b110 /
b110 c
b1 +
b1 _
b111 :
b110 5
b110 B
b1 4
b1 X
b111000000010000010000000110 "
b111000000010000010000000110 &
b1001 .
b1001 K
b1001 O
b1001 R
b1001 W
b1001 `
#48
0<
18
b1001 I
b1001 Q
0#
#49
b1000 6
b1000 L
b1000 ^
b11100 ,
b11100 ?
b11100 Z
b1000 J
b1000 N
#52
1#
#53
b11000 !
b11000 ;
b11000 \
#54
b11100 2
b11100 A
b11100 1
b11100 @
b11100 [
b11100 ]
#55
b0 0
b0 a
b0 /
b0 c
b101 +
b101 _
b1111111111111111111111 Y
b110 :
b0 5
b0 B
b11111101 4
b11111101 X
b110111111010000000000000000 "
b110111111010000000000000000 &
#56
1)
08
19
0#
#57
b10000 2
b10000 A
b0 .
b0 K
b0 O
b0 R
b0 W
b0 `
b0 -
b0 b
b0 e
b0 g
b10000 ,
b10000 ?
b10000 Z
#58
b0 3
b0 D
b0 E
b0 M
b0 P
b0 S
b0 U
b0 '
b0 C
b0 i
b0 I
b0 Q
b0 (
b0 f
b0 h
#59
b0 G
b0 V
b0 H
b0 T
#60
1*
b0 6
b0 L
b0 ^
b0 J
b0 N
1#
#61
b10000 !
b10000 ;
b10000 \
#62
b10100 1
b10100 @
b10100 [
b10100 ]
#63
b100 0
b100 a
b101 /
b101 c
b100 +
b100 _
b0 Y
b11 :
b101 5
b101 B
b100 4
b100 X
b11000001000000010000000101 "
b11000001000000010000000101 &
#64
b10100 2
b10100 A
0)
1<
09
0#
#65
b1001 .
b1001 K
b1001 O
b1001 R
b1001 W
b1001 `
b1 -
b1 b
b1 e
b1 g
b100100 ,
b100100 ?
b100100 Z
#66
b11111111 3
b11111111 D
b11111111 E
b11111111 M
b11111111 P
b11111111 S
b11111111 U
b11111111 '
b11111111 C
b11111111 i
b1001 G
b1001 V
b11111111 (
b11111111 f
b11111111 h
#67
b1001 I
b1001 Q
b11111111 G
b11111111 V
b11111111 H
b11111111 T
#68
0*
b1000 6
b1000 L
b1000 ^
b1000 J
b1000 N
1#
#69
b1000 n
b10100 !
b10100 ;
b10100 \
