Part 2/group49_lab5_part2/reg_file.v
// Computer Architecture (CO224) - Lab 05 Part-2
// Design: Register File of Simple Processor
// Group: Group-49 
// Reg. No.: E/19/038 and E/19/256

`timescale 1ns/1ns
module reg_file (
    input[7:0] IN,                // Input data
    output[7:0] OUT1,             // Output data 1
    output[7:0] OUT2,             // Output data 2
    input[2:0] INADDRESS,         // Input address 
    input[2:0] OUT1ADDRESS,       // Output 1 address 
    input[2:0] OUT2ADDRESS,       // Output 2 address 
    input WRITE,                  // Write control signal
    input CLK,                    // Clock signal
    input RESET                   // Reset control signal
);

    // Declaration of register file by using 8 element array of 8 bit registers
    reg [7:0] register[0:7];    
    
    // These assign statements are executed asynchronously (data transmitted concurrently).
    // There are artificial delays of two time units for register reading.
    assign #2 OUT1 = register[OUT1ADDRESS];    // Assigning output 1 from register file
    assign #2 OUT2 = register[OUT2ADDRESS];    // Assigning output 2 from register file

    integer i; 
    
    // This block is works in synchronous manner 
    // this is work during the rising edge of the clock pulse.
    always @(posedge CLK) 
    begin
        if (RESET) 
        begin
            // For loop set all register values to zero ( when the RESET signal is in a high state)

            #1  // Artificial delay of one time unit for resetting
            for (i = 0; i < 8; i = i + 1) 
            begin
                register[i] <= 0;    // Resetting register values
            end
        end
        else 
        begin
            // The else condition handles data transfer when WRITE is high.
            // It transfers data from the input IN to the register specified by the address INADDRESS.
            if (WRITE) 
            #1 
            register[INADDRESS] <= IN;    // Writing data into the specified register
            // Artificial delays of one time units for register writing
        end
    end
endmodule

Part 2/group49_lab5_part2/reg_file_tb.v
// Computer Architecture (CO224) - Lab 05 Part-2
// Design: Testbench-Register File of Simple Processor
// Author: Kisaru Liyanage
// Group: Group-49 
// Edited by: E/19/256 and E/19/038

`timescale 1ns / 1ns    
`include "reg_file.v"     // Including the reg_file module

module reg_file_tb;

    reg [7:0] WRITEDATA;    // Data to be written to register file
    reg [2:0] WRITEREG, READREG1, READREG2;   // Write and read register addresses
    reg CLK, RESET, WRITEENABLE;   // Clock, reset, and write enable signals
    wire [7:0] REGOUT1, REGOUT2;   // Output data from register file

    // Instantiation of the reg_file module
    reg_file myregfile(     
        WRITEDATA,          // Input data
        REGOUT1, REGOUT2,   // Output data
        WRITEREG,           // Input address for writing
        READREG1, READREG2, // Input addresses for reading
        WRITEENABLE,        // Write enable signal
        CLK, RESET          // Clock and reset signals
    );
       
    initial begin
        CLK = 1'b1;  // Initial value for clock
        
        $dumpfile("reg_file_wavedata.vcd"); // Create VCD file for waveform dumping
        $dumpvars(0, reg_file_tb); // Dump variables for waveform
        
        // assign values with time to input signals to see output 
        RESET = 1'b0;  
        
        WRITEENABLE = 1'b0; 
        
        #4  
        
        RESET = 1'b1;   
        READREG1 = 3'd0;    
        READREG2 = 3'd4;    
        
        #6   
        
        RESET = 1'b0;   
        
        #2   
        WRITEREG = 3'd2;   
        WRITEDATA = 8'd95;  
        WRITEENABLE = 1'b1;
        
        #7   
        WRITEENABLE = 1'b0;
        
        #1   
        READREG1 = 3'd2;   
        
        #7  
        WRITEREG = 3'd1;    
        WRITEDATA = 8'd28;
        WRITEENABLE = 1'b1; 
        READREG1 = 3'd1;    
        
        #8   
        WRITEENABLE = 1'b0; 
        
        #8   
        WRITEREG = 3'd4;   
        WRITEDATA = 8'd6;   
        WRITEENABLE = 1'b1; 
        
        #8   
        WRITEDATA = 8'd15; 
        WRITEENABLE = 1'b1; 
        
        #10  
        WRITEENABLE = 1'b0; 
        
        #6   
        WRITEREG = -3'd1; 
        WRITEDATA = 8'd50;  
        WRITEENABLE = 1'b1; 
        
        #5  
        WRITEENABLE = 1'b0; 
        
        #10  
        $finish;    
    end
    
    // Clock signal generation
    always
        #4 CLK = ~CLK; 
endmodule

Part 2/group49_lab5_part2/reg_file_wavedata.vcd
$date
	Wed Apr 10 23:03:01 2024
$end
$version
	Icarus Verilog
$end
$timescale
	1ns
$end
$scope module reg_file_tb $end
$var wire 8 ! REGOUT2 [7:0] $end
$var wire 8 " REGOUT1 [7:0] $end
$var reg 1 # CLK $end
$var reg 3 $ READREG1 [2:0] $end
$var reg 3 % READREG2 [2:0] $end
$var reg 1 & RESET $end
$var reg 8 ' WRITEDATA [7:0] $end
$var reg 1 ( WRITEENABLE $end
$var reg 3 ) WRITEREG [2:0] $end
$scope module myregfile $end
$var wire 1 # CLK $end
$var wire 8 * IN [7:0] $end
$var wire 3 + INADDRESS [2:0] $end
$var wire 8 , OUT1 [7:0] $end
$var wire 3 - OUT1ADDRESS [2:0] $end
$var wire 8 . OUT2 [7:0] $end
$var wire 3 / OUT2ADDRESS [2:0] $end
$var wire 1 & RESET $end
$var wire 1 ( WRITE $end
$var integer 32 0 i [31:0] $end
$upscope $end
$upscope $end
$enddefinitions $end
$comment Show the parameter values. $end
$dumpall
$end
#0
$dumpvars
bx 0
bx /
bx .
bx -
bx ,
bx +
bx *
bx )
0(
bx '
0&
bx %
bx $
1#
bx "
bx !
$end
#4
0#
b100 %
b100 /
b0 $
b0 -
1&
#8
1#
#9
b1000 0
#10
0&
#11
b0 !
b0 .
b0 "
b0 ,
#12
1(
b1011111 '
b1011111 *
b10 )
b10 +
0#
#16
1#
#19
0(
#20
b10 $
b10 -
0#
#22
b1011111 "
b1011111 ,
#24
1#
#27
b1 $
b1 -
1(
b11100 '
b11100 *
b1 )
b1 +
#28
0#
#29
b0 "
b0 ,
#32
1#
#35
b11100 "
b11100 ,
0(
#36
0#
#40
1#
#43
1(
b110 '
b110 *
b100 )
b100 +
#44
0#
#48
1#
#51
b110 !
b110 .
b1111 '
b1111 *
#52
0#
#56
1#
#59
b1111 !
b1111 .
#60
0#
#61
0(
#64
1#
#67
1(
b110010 '
b110010 *
b111 )
b111 +
#68
0#
#72
1#
0(
