Part 3/Other_modules.v
// Computer Architecture (CO224) - Lab 05 Part-2
// Design: Secondary parts (MUX, Twos'complement)
// Group: Group-49 
// Reg. No.: E/19/038 and E/19/256


// Module for Twos'complement
//The twosComp module returns the 2's complement value of the input as the output after a delay of 1 time unit
module twosComp(IN, OUT);

	input [7:0] IN;    // Input
	output [7:0] OUT;  // Output
	
	//Combinational logic to assign two's complement value of input to output after a delay of #1
	assign #1 OUT = ~IN + 1;

endmodule


// Module for MUX unit
//Generic MUX module to be used inside the CPU
//Operation: SELECT == 0 : OUT = IN1
//			 SELECT == 1 : OUT = IN2
//Does not contain delays
module mux(IN1, IN2, SELECT, OUT);

	//Input and output port declaration
	input [7:0] IN1;       // Input DATA
	input [7:0] IN2;       // Input DATA
	input SELECT;          // Input port for SELECT
	output reg [7:0] OUT;  // Output DATA
	
	//MUX should update output value upon change of any of the inputs
	always @ (IN1, IN2, SELECT)
	begin
		if (SELECT == 1'b1)		//If SELECT is HIGH, switch to 2nd input
		begin
			OUT = IN2;
		end
		else					//If SELECT is LOW, switch to 1st input
		begin
			OUT = IN1;
		end
	end

endmodule

Part 4/or.v
// Computer Architecture (CO224) - Lab 05 Part-1
// Design: OR module
// Group: Group-49 
// Reg. No.: E/19/038 and E/19/256


// Module for OR unit
module OR(DATA1, DATA2, RESULT);

	input [7:0] DATA1;    // Input data 1 for addition
    input [7:0] DATA2;    // Input data 2 for addition
	output [7:0] RESULT;  // Output result for addition
	
	//Assigns logical OR result of DATA1 and DATA2 to RESULT after 1 time unit delay
	assign #1 RESULT = DATA1 | DATA2;
	
endmodule

Part 3/and.v
// Computer Architecture (CO224) - Lab 05 Part-1
// Design: AND module
// Group: Group-49 
// Reg. No.: E/19/038 and E/19/256


// Module for AND unit
module AND(DATA1, DATA2, RESULT);

	input [7:0] DATA1;    // Input data 1 for addition
    input [7:0] DATA2;    // Input data 2 for addition
	output [7:0] RESULT;  // Output result for addition
	
	//Assigns logical AND result of DATA1 and DATA2 to RESULT after 1 time unit delay
	assign #1 RESULT = DATA1 & DATA2;
	
endmodule

Part 4/add.v
// Computer Architecture (CO224) - Lab 05 Part-1
// Design: ADD module
// Group: Group-49 
// Reg. No.: E/19/038 and E/19/256


// Module for ADD unit
module ADD(DATA1, DATA2, RESULT);

	input [7:0] DATA1;    // Input data 1 for addition
    input [7:0] DATA2;    // Input data 2 for addition
	output [7:0] RESULT;  // Output result for addition
	
	//Assigns evaluated addition of DATA1 and DATA2 to RESULT after 2 time unit delay
	assign #2 RESULT = DATA1 + DATA2;
	
endmodule

Part 3/forward.v
// Computer Architecture (CO224) - Lab 05 Part-1
// Design: FORWARD module
// Group: Group-49 
// Reg. No.: E/19/038 and E/19/256


// Module for FORWARD unit
module FORWARD(DATA, RESULT);

	input [7:0] DATA;    // Input data for addition
	output [7:0] RESULT;  // Output result for addition
	
	//Assigns the value of DATA to RESULT after a delay of 1 time unit
	assign #1 RESULT = DATA;

endmodule

Part 3/alu.v
// Computer Architecture (CO224) - Lab 05 Part-1
// Design: ALU of Simple Processor
// Group: Group-49 
// Reg. No.: E/19/038 and E/19/256

`include "add.v"
`include"forward.v"
`include "and.v"
`include "or.v"

// Module for ALU
module alu(DATA1, DATA2, RESULT, SELECT);
	
	input [7:0] DATA1; // Input port for DATA1, an 8-bit vector.
    input [7:0] DATA2; // Input port for DATA2, an 8-bit vector.
    input [2:0] SELECT; // Input port for SELECT, a 3-bit vector.
    output reg [7:0] RESULT; // Output port for RESULT, an 8-bit vector.
	
    // Internal signals for functional units
	wire [7:0] forwardOut; // Internal register to hold the result for the FORWARD operation.
	wire [7:0] addOut;     // Internal register to hold the result for the ADD operation.
	wire [7:0] andOut;     // Internal register to hold the result for the AND operation.
	wire [7:0] orOut;      // Internal register to hold the result for the OR operation.
	
	
	// Instantiation of functional unit modules
	FORWARD forwardUnit(DATA2, forwardOut); // Instantiate FORWARD unit
	ADD addUnit(DATA1, DATA2, addOut);      // Instantiate ADD unit
	AND andUnit(DATA1, DATA2, andOut);      // Instantiate AND unit
	OR orUnit(DATA1, DATA2, orOut);         // Instantiate OR unit
	
	
    // Output selection using a MUX
	//One of the functional units' results is sent to the RESULT output based on the SELECT value
	always @* //(forwardOut, addOut, andOut, orOut, SELECT)	
	begin
		case (SELECT)
			3'b000 :	RESULT = forwardOut;	// If SELECT is 000, output forward_result.
			3'b001 :	RESULT = addOut;		// If SELECT is 001, output add_result.
			3'b010 :	RESULT = andOut;		// If SELECT is 010, output and_result.
			3'b011 :	RESULT = orOut;			// If SELECT is 011, output or_result.
			
		endcase
	end
		
endmodule

Part 3/reg_file.v
// Computer Architecture (CO224) - Lab 05 Part-2
// Design: Register File of Simple Processor
// Group: Group-49 
// Reg. No.: E/19/038 and E/19/256

module reg_file(IN,OUT1,OUT2,INADDRESS,OUT1ADDRESS,OUT2ADDRESS, WRITE, CLK, RESET);

	input[7:0] IN;                // Input data
    output [7:0] OUT1;            // Output data 1
    output [7:0] OUT2;            // Output data 2
    input[2:0] INADDRESS;         // Input address 
    input[2:0] OUT1ADDRESS;       // Output 1 address 
    input[2:0] OUT2ADDRESS;       // Output 2 address 
    input WRITE;                  // Write control signal
    input CLK;                    // Clock signal
    input RESET;                  // Reset control signal
	
    // Declaration of register file by using 8 element array of 8 bit registers
	reg [7:0] REGISTER [7:0];

	//Iterator variable used in for loop
	integer i;
	
	// These assign statements are executed asynchronously (data transmitted concurrently).
    // There are artificial delays of two time units for register reading.
	assign #2 OUT1 = REGISTER[OUT1ADDRESS];		// Assigning output 1 from register file
	assign #2 OUT2 = REGISTER[OUT2ADDRESS];		// Assigning output 2 from register file
	
	
	// This block is works in synchronous manner 
    // this is work during the rising edge of the clock pulse.
	always @ (posedge CLK)
	begin
		if (RESET == 1'b1)		//If the RESET signal is HIGH, registers must be cleared
		begin
		
			#1 // Artificial delay of one time unit for resetting
            for (i = 0; i < 8; i = i + 1)			//For loop to iterate over all 8 register addresses after 1 time unit delay
			begin
				REGISTER[i] = 8'b00000000;		//Setting each element of the REGISTER array to 0
			end
			
		end
		else if (WRITE == 1'b1)			// The else condition handles data transfer when WRITE is high.
                                        // It transfers data from the input IN to the register specified by the address INADDRESS.
		begin
			#1 // Artificial delays of one time units for register writing
            REGISTER[INADDRESS] = IN;		//Assigns the input value IN to relevant register address 
		end
	end
	
	initial begin
			$monitor($time, "\t%d\t%d", OUT1,OUT2);
		end
	

endmodule

Part 3/cpu.v
// Computer Architecture (CO224) - Lab 05 Part-3
// Design: CPU of Simple Processor
// Group: Group-49 
// Reg. No.: E/19/038 and E/19/256

`include "alu.v"
`include "reg_file.v"
`include "Other_modules.v"

//The CPU module contains all the necessary components of the CPU
//The various sub-modules of the CPU are instantiated within the module
//The control logic for the operation of the CPU exists within this top module
module cpu(PC, INSTRUCTION, CLK, RESET);

    input [31:0] INSTRUCTION;     // Input Instruction
    input CLK;                    // Clock signal
    input RESET;                  // Reset control signal
    
    output reg [31:0] PC;         // Output PC
    
    wire [2:0] READREG1;          // Read register 1 address
    wire [2:0] READREG2;          // Read register 2 address
    wire [2:0] WRITEREG;          // Write register address
    wire [7:0] REGOUT1;           // Data from register 1
    wire [7:0] REGOUT2;           // Data from register 2
    reg WRITEENABLE;              // Write enable control
    
    wire [7:0] OPERAND1;          // Operand 1 for ALU
    wire [7:0] OPERAND2;          // Operand 2 for ALU
    wire [7:0] ALURESULT;         // Result from ALU
    reg [2:0] ALUOP;              // ALU operation control
    
    wire [7:0] negatedOp;         // Negated operand for ALU
    wire [7:0] registerOp;        // Operand from register for ALU
    reg signSelect;               // Sign selection control
    
    wire [7:0] IMMEDIATE;         // Immediate value
    reg immSelect;                // Immediate selection control
    
    reg [31:0] PCreg;             // Register for holding PC
    
    reg [7:0] OPCODE;             // Opcode

	
	//Instantiation of CPU modules
	reg_file my_reg(ALURESULT, REGOUT1, REGOUT2, WRITEREG, READREG1, READREG2, WRITEENABLE, CLK, RESET);
	alu my_alu(REGOUT1, OPERAND2, ALURESULT, ALUOP);
	twosComp my_twosComp(REGOUT2, negatedOp);
	mux negationMUX(REGOUT2, negatedOp, signSelect, registerOp);
	mux immediateMUX(registerOp, IMMEDIATE, immSelect, OPERAND2);

	// Control Logic for CPU
	
	//PC Update (Fetching Mechanism)
	always @ ( posedge CLK)
	begin
		if (RESET == 1'b1) 
		begin
			#1
			PC = 0;		//If RESET signal is HIGH, set PC to zero
			PCreg = 0;
		end
		else #1 PC = PCreg;		//Else, write new PC value
	end
	
	
	//PC+4 Adder
	always @ (PC)
	begin
		#1 PCreg = PCreg + 4;
	end
	
	
	//Relevant portions of INSTRUCTION are mapped to the respective units
	
	///////////////////////////////////////////////////////////////////
	/*    OP-CODE    /      RD       /       RT      /     RS/IMM    */
	/*    [31:24]    /    [23:16]    /     [15:8]    /      [7:0]    */
	///////////////////////////////////////////////////////////////////
	/*       |       /        |      /        |      /       |       */
	/*    OPCODE     /    WRITEREG   /    READREG1   /    READREG2   */
	/*               /               /               /   IMMEDIATE   */
	/*****************************************************************/
	assign READREG1 = INSTRUCTION[15:8];
	assign IMMEDIATE = INSTRUCTION[7:0];
	assign READREG2 = INSTRUCTION[7:0];
	assign WRITEREG = INSTRUCTION[23:16];
	
	//Decoding the instruction
	always @ (INSTRUCTION)
	begin
	
		OPCODE = INSTRUCTION[31:24];	//Mapping the OP-CODE section of the instruction to OPCODE
		
		#1			//1 Time Unit Delay for Decoding process
		
		case (OPCODE)
		
			//loadi instruction
			8'b00000000:	begin
								ALUOP = 3'b000;			//Set ALU to forward
								immSelect = 1'b1;		//Set MUX to select immediate value
								signSelect = 1'b0;		//Set sign select MUX to positive sign
								WRITEENABLE = 1'b1;		//Enable writing to register
							end
		
			//mov instruction
			8'b00000001:	begin
								ALUOP = 3'b000;			//Set ALU to FORWARD
								immSelect = 1'b0;		//Set MUX to select register input
								signSelect = 1'b0;		//Set sign select MUX to positive sign
								WRITEENABLE = 1'b1;		//Enable writing to register
							end
			
			//add instruction
			8'b00000010:	begin
								ALUOP = 3'b001;			//Set ALU to ADD
								immSelect = 1'b0;		//Set MUX to select register input
								signSelect = 1'b0;		//Set sign select MUX to positive sign
								WRITEENABLE = 1'b1;		//Enable writing to register
							end	
		
			//sub instruction
			8'b00000011:	begin
								ALUOP = 3'b001;			//Set ALU to ADD
								immSelect = 1'b0;		//Set MUX to select register input
								signSelect = 1'b1;		//Set sign select MUX to negative sign
								WRITEENABLE = 1'b1;		//Enable writing to register
							end

			//and instruction
			8'b00000100:	begin
								ALUOP = 3'b010;			//Set ALU to AND
								immSelect = 1'b0;		//Set MUX to select register input
								signSelect = 1'b0;		//Set sign select MUX to positive sign
								WRITEENABLE = 1'b1;		//Enable writing to register
							end
							
			//or operation
			8'b00000101:	begin
								ALUOP = 3'b011;			//Set ALU to OR
								immSelect = 1'b0;		//Set MUX to select register input
								signSelect = 1'b0;		//Set sign select MUX to positive sign
								WRITEENABLE = 1'b1;		//Enable writing to register
							end

		endcase
		
	end
	
endmodule

Part 3/cpu_tb.v
// Computer Architecture (CO224) - Lab 05
// Design: Testbench of Integrated CPU of Simple Processor
// Author: Kisaru Liyanage
`include "cpu.v"

module cpu_tb;

    reg CLK, RESET;
    wire [31:0] PC;
    wire [31:0] INSTRUCTION;
    integer i;
    
    /* 
    ------------------------
     SIMPLE INSTRUCTION MEM
    ------------------------
    */
    
    // TODO: Initialize an array of registers (8x1024) named 'instr_mem' to be used as instruction memory
	reg [7:0] instr_mem [1023:0];
    
    // TODO: Create combinational logic to support CPU instruction fetching, given the Program Counter(PC) value 
    //       (make sure you include the delay for instruction fetching here)
	assign #2 INSTRUCTION = {instr_mem[PC+3], instr_mem[PC+2], instr_mem[PC+1], instr_mem[PC]};
    
    initial
    begin
        // Initialize instruction memory with the set of instructions you need execute on CPU
        
        // METHOD 1: manually loading instructions to instr_mem
        //{instr_mem[10'd3], instr_mem[10'd2], instr_mem[10'd1], instr_mem[10'd0]} = 32'b00000000000001000000000000000101;
        //{instr_mem[10'd7], instr_mem[10'd6], instr_mem[10'd5], instr_mem[10'd4]} = 32'b00000000000000100000000000001001;
        //{instr_mem[10'd11], instr_mem[10'd10], instr_mem[10'd9], instr_mem[10'd8]} = 32'b00000010000001100000010000000010;
        
        // METHOD 2: loading instr_mem content from instr_mem.mem file
        $readmemb("instr_mem.mem", instr_mem);
    end
    
    /* 
    -----
     CPU
    -----
    */
    cpu mycpu(PC, INSTRUCTION, CLK, RESET);

    /* START DEBUGGING CODE*/
    initial 
    begin 
    // monitor changes in reg file content and print (used to check whether the CPU is running properly)
    #5;
    $display("\n\t\t\t==================================================");
    $display("\t\t\t Change of register Content Starting from Time #5");
    $display("\t\t\t==================================================\n");
    $display("\t\ttime\treg0\treg1\treg2\treg3\treg4\treg5\treg6\treg7");
    $display("\t\t----------------------------------------------------------------------");
    $monitor($time, "\t%d\t%d\t%d\t%d\t%d\t%d\t%d\t%d", mycpu.my_reg.REGISTER[0], mycpu.my_reg.REGISTER[1], mycpu.my_reg.REGISTER[2], mycpu.my_reg.REGISTER[3], mycpu.my_reg.REGISTER[4], mycpu.my_reg.REGISTER[5], mycpu.my_reg.REGISTER[6], mycpu.my_reg.REGISTER[7]);
    end

    initial
    begin
    
        // generate files needed to plot the waveform using GTKWave
        $dumpfile("cpu_wavedata.vcd");
		$dumpvars(0, cpu_tb);
        for (i=0; i<8; i=1+i)
            $dumpvars(1, mycpu.my_reg.REGISTER[i]);
        
        CLK = 1'b0;

        // TODO: Reset the CPU (by giving a pulse to RESET signal) to start the program execution
		RESET = 1'b1;
		#5
		RESET = 1'b0;
        
        // finish simulation after some time
        #300
        $finish;
        
    end
    
    // clock signal generation
    always
        #4 CLK = ~CLK;
        

endmodule

Part 3/cpu_wavedata.vcd
$date
	Mon May 20 19:56:40 2024
$end
$version
	Icarus Verilog
$end
$timescale
	1s
$end
$scope module cpu_tb $end
$var wire 32 ! PC [31:0] $end
$var wire 32 " INSTRUCTION [31:0] $end
$var reg 1 # CLK $end
$var reg 1 $ RESET $end
$var integer 32 % i [31:0] $end
$scope module mycpu $end
$var wire 1 # CLK $end
$var wire 32 & INSTRUCTION [31:0] $end
$var wire 1 $ RESET $end
$var wire 8 ' registerOp [7:0] $end
$var wire 8 ( negatedOp [7:0] $end
$var wire 3 ) WRITEREG [2:0] $end
$var wire 8 * REGOUT2 [7:0] $end
$var wire 8 + REGOUT1 [7:0] $end
$var wire 3 , READREG2 [2:0] $end
$var wire 3 - READREG1 [2:0] $end
$var wire 8 . OPERAND2 [7:0] $end
$var wire 8 / IMMEDIATE [7:0] $end
$var wire 8 0 ALURESULT [7:0] $end
$var reg 3 1 ALUOP [2:0] $end
$var reg 8 2 OPCODE [7:0] $end
$var reg 32 3 PC [31:0] $end
$var reg 32 4 PCreg [31:0] $end
$var reg 1 5 WRITEENABLE $end
$var reg 1 6 immSelect $end
$var reg 1 7 signSelect $end
$scope module immediateMUX $end
$var wire 8 8 IN2 [7:0] $end
$var wire 1 6 SELECT $end
$var wire 8 9 IN1 [7:0] $end
$var reg 8 : OUT [7:0] $end
$upscope $end
$scope module my_alu $end
$var wire 8 ; DATA2 [7:0] $end
$var wire 3 < SELECT [2:0] $end
$var wire 8 = orOut [7:0] $end
$var wire 8 > forwardOut [7:0] $end
$var wire 8 ? andOut [7:0] $end
$var wire 8 @ addOut [7:0] $end
$var wire 8 A DATA1 [7:0] $end
$var reg 8 B RESULT [7:0] $end
$scope module addUnit $end
$var wire 8 C DATA2 [7:0] $end
$var wire 8 D RESULT [7:0] $end
$var wire 8 E DATA1 [7:0] $end
$upscope $end
$scope module andUnit $end
$var wire 8 F DATA2 [7:0] $end
$var wire 8 G RESULT [7:0] $end
$var wire 8 H DATA1 [7:0] $end
$upscope $end
$scope module forwardUnit $end
$var wire 8 I DATA [7:0] $end
$var wire 8 J RESULT [7:0] $end
$upscope $end
$scope module orUnit $end
$var wire 8 K DATA2 [7:0] $end
$var wire 8 L RESULT [7:0] $end
$var wire 8 M DATA1 [7:0] $end
$upscope $end
$upscope $end
$scope module my_reg $end
$var wire 1 # CLK $end
$var wire 8 N IN [7:0] $end
$var wire 3 O INADDRESS [2:0] $end
$var wire 8 P OUT1 [7:0] $end
$var wire 3 Q OUT1ADDRESS [2:0] $end
$var wire 8 R OUT2 [7:0] $end
$var wire 3 S OUT2ADDRESS [2:0] $end
$var wire 1 $ RESET $end
$var wire 1 5 WRITE $end
$var integer 32 T i [31:0] $end
$upscope $end
$scope module my_twosComp $end
$var wire 8 U IN [7:0] $end
$var wire 8 V OUT [7:0] $end
$upscope $end
$scope module negationMUX $end
$var wire 8 W IN1 [7:0] $end
$var wire 8 X IN2 [7:0] $end
$var wire 1 7 SELECT $end
$var reg 8 Y OUT [7:0] $end
$upscope $end
$upscope $end
$upscope $end
$scope module cpu_tb $end
$scope module mycpu $end
$scope module my_reg $end
$var reg 8 Z \REGISTER[0] [7:0] $end
$upscope $end
$upscope $end
$upscope $end
$scope module cpu_tb $end
$scope module mycpu $end
$scope module my_reg $end
$var reg 8 [ \REGISTER[1] [7:0] $end
$upscope $end
$upscope $end
$upscope $end
$scope module cpu_tb $end
$scope module mycpu $end
$scope module my_reg $end
$var reg 8 \ \REGISTER[2] [7:0] $end
$upscope $end
$upscope $end
$upscope $end
$scope module cpu_tb $end
$scope module mycpu $end
$scope module my_reg $end
$var reg 8 ] \REGISTER[3] [7:0] $end
$upscope $end
$upscope $end
$upscope $end
$scope module cpu_tb $end
$scope module mycpu $end
$scope module my_reg $end
$var reg 8 ^ \REGISTER[4] [7:0] $end
$upscope $end
$upscope $end
$upscope $end
$scope module cpu_tb $end
$scope module mycpu $end
$scope module my_reg $end
$var reg 8 _ \REGISTER[5] [7:0] $end
$upscope $end
$upscope $end
$upscope $end
$scope module cpu_tb $end
$scope module mycpu $end
$scope module my_reg $end
$var reg 8 ` \REGISTER[6] [7:0] $end
$upscope $end
$upscope $end
$upscope $end
$scope module cpu_tb $end
$scope module mycpu $end
$scope module my_reg $end
$var reg 8 a \REGISTER[7] [7:0] $end
$upscope $end
$upscope $end
$upscope $end
$enddefinitions $end
$comment Show the parameter values. $end
$dumpall
$end
#0
$dumpvars
bx a
bx `
bx _
bx ^
bx ]
bx \
bx [
bx Z
bx Y
bx X
bx W
bx V
bx U
bx T
bx S
bx R
bx Q
bx P
bx O
bx N
bx M
bx L
bx K
bx J
bx I
bx H
bx G
bx F
bx E
bx D
bx C
bx B
bx A
bx @
bx ?
bx >
bx =
bx <
bx ;
bx :
bx 9
bx 8
x7
x6
x5
bx 4
bx 3
bx 2
bx 1
bx 0
bx /
bx .
bx -
bx ,
bx +
bx *
bx )
bx (
bx '
bx &
b1000 %
1$
0#
bx "
bx !
$end
#4
1#
#5
b0 a
b0 `
b0 _
b0 ^
b0 ]
b0 \
b0 [
b0 Z
b1000 T
b0 4
b0 !
b0 3
0$
#6
b100 4
#7
b0 -
b0 Q
b101 ,
b101 S
b100 )
b100 O
b0 2
b101 /
b101 8
b1000000000000000101 "
b1000000000000000101 &
#8
b101 .
b101 :
b101 ;
b101 C
b101 F
b101 I
b101 K
15
07
16
b0 1
b0 <
0#
#9
b101 0
b101 B
b101 N
b0 '
b0 9
b0 Y
b0x0x ?
b0x0x G
bx1x1 =
bx1x1 L
b101 >
b101 J
b0 +
b0 A
b0 E
b0 H
b0 M
b0 P
b0 *
b0 R
b0 U
b0 W
#10
b101 =
b101 L
b0 ?
b0 G
b0 (
b0 V
b0 X
#11
b101 @
b101 D
#12
1#
#13
b100 !
b100 3
b101 ^
#14
b1000 4
#15
b1001 .
b1001 :
b1001 ;
b1001 C
b1001 F
b1001 I
b1001 K
b1 ,
b1 S
b10 )
b10 O
b1001 /
b1001 8
b100000000000001001 "
b100000000000001001 &
#16
b1001 0
b1001 B
b1001 N
b1001 =
b1001 L
b1001 >
b1001 J
0#
#17
b1001 @
b1001 D
#20
1#
#21
b1001 \
b1000 !
b1000 3
#22
b1100 4
#23
b100 -
b100 Q
b10 .
b10 :
b10 ;
b10 C
b10 F
b10 I
b10 K
b10 ,
b10 S
b110 )
b110 O
b10 2
b10 /
b10 8
b10000001100000010000000010 "
b10000001100000010000000010 &
#24
b0 .
b0 :
b0 ;
b0 C
b0 F
b0 I
b0 K
b10 =
b10 L
b10 >
b10 J
06
b1 1
b1 <
0#
#25
b1001 .
b1001 :
b1001 ;
b1001 C
b1001 F
b1001 I
b1001 K
b1001 '
b1001 9
b1001 Y
b0 =
b0 L
b0 >
b0 J
b101 +
b101 A
b101 E
b101 H
b101 M
b101 P
b1001 *
b1001 R
b1001 U
b1001 W
#26
b1 ?
b1 G
b1001 >
b1001 J
b1101 =
b1101 L
b11110111 (
b11110111 V
b11110111 X
#27
b1110 0
b1110 B
b1110 N
b1110 @
b1110 D
#28
1#
#29
b1100 !
b1100 3
b1110 `
#30
b10000 4
#31
b0 -
b0 Q
b110 ,
b110 S
b0 )
b0 O
b1 2
b110 /
b110 8
b1000000000000000000000110 "
b1000000000000000000000110 &
#32
b1001 0
b1001 B
b1001 N
b0 1
b0 <
0#
#33
b1110 .
b1110 :
b1110 ;
b1110 C
b1110 F
b1110 I
b1110 K
b1110 '
b1110 9
b1110 Y
b0 +
b0 A
b0 E
b0 H
b0 M
b0 P
b1110 *
b1110 R
b1110 U
b1110 W
#34
b1110 0
b1110 B
b1110 N
b1110 >
b1110 J
b1110 =
b1110 L
b0 ?
b0 G
b11110010 (
b11110010 V
b11110010 X
#36
1#
#37
b1110 Z
b10000 !
b10000 3
#38
b10100 4
#39
b1 ,
b1 S
b1 )
b1 O
b0 2
b1 /
b1 8
b1110 +
b1110 A
b1110 E
b1110 H
b1110 M
b1110 P
b10000000000000001 "
b10000000000000001 &
#40
b1 .
b1 :
b1 ;
b1 C
b1 F
b1 I
b1 K
b1110 ?
b1110 G
16
0#
#41
b1 0
b1 B
b1 N
b0 '
b0 9
b0 Y
b0 ?
b0 G
b1111 =
b1111 L
b1 >
b1 J
b0 *
b0 R
b0 U
b0 W
#42
b0 (
b0 V
b0 X
b1111 @
b1111 D
#44
1#
#45
b10100 !
b10100 3
b1 [
#46
b11000 4
#47
b10 -
b10 Q
b10 )
b10 O
b10 2
b1 '
b1 9
b1 Y
b10000000100000001000000001 "
b10000000100000001000000001 &
b1 *
b1 R
b1 U
b1 W
#48
b1111 0
b1111 B
b1111 N
06
b1 1
b1 <
b11111111 (
b11111111 V
b11111111 X
0#
#49
b1001 +
b1001 A
b1001 E
b1001 H
b1001 M
b1001 P
#50
b1001 =
b1001 L
b1 ?
b1 G
#51
b1010 0
b1010 B
b1010 N
b1010 @
b1010 D
#52
1#
#53
b1010 \
b11000 !
b11000 3
#54
b11100 4
#55
bx -
bx Q
bx ,
bx S
bx )
bx O
bx 2
bx /
bx 8
b1010 +
b1010 A
b1010 E
b1010 H
b1010 M
b1010 P
bx "
bx &
#56
b1011 =
b1011 L
b0 ?
b0 G
0#
#57
bx .
bx :
bx ;
bx C
bx F
bx I
bx K
bx '
bx 9
bx Y
b1011 0
b1011 B
b1011 N
bx +
bx A
bx E
bx H
bx M
bx P
bx *
bx R
bx U
bx W
b1011 @
b1011 D
#58
bx >
bx J
bx =
bx L
bx ?
bx G
bx (
bx V
bx X
#59
bx 0
bx B
bx N
bx @
bx D
#60
1#
#61
b11100 !
b11100 3
#62
b100000 4
#64
0#
#68
1#
#69
b100000 !
b100000 3
#70
b100100 4
#72
0#
#76
1#
#77
b100100 !
b100100 3
#78
b101000 4
#80
0#
#84
1#
#85
b101000 !
b101000 3
#86
b101100 4
#88
0#
#92
1#
#93
b101100 !
b101100 3
#94
b110000 4
#96
0#
#100
1#
#101
b110000 !
b110000 3
#102
b110100 4
#104
0#
#108
1#
#109
b110100 !
b110100 3
#110
b111000 4
#112
0#
#116
1#
#117
b111000 !
b111000 3
#118
b111100 4
#120
0#
#124
1#
#125
b111100 !
b111100 3
#126
b1000000 4
#128
0#
#132
1#
#133
b1000000 !
b1000000 3
#134
b1000100 4
#136
0#
#140
1#
#141
b1000100 !
b1000100 3
#142
b1001000 4
#144
0#
#148
1#
#149
b1001000 !
b1001000 3
#150
b1001100 4
#152
0#
#156
1#
#157
b1001100 !
b1001100 3
#158
b1010000 4
#160
0#
#164
1#
#165
b1010000 !
b1010000 3
#166
b1010100 4
#168
0#
#172
1#
#173
b1010100 !
b1010100 3
#174
b1011000 4
#176
0#
#180
1#
#181
b1011000 !
b1011000 3
#182
b1011100 4
#184
0#
#188
1#
#189
b1011100 !
b1011100 3
#190
b1100000 4
#192
0#
#196
1#
#197
b1100000 !
b1100000 3
#198
b1100100 4
#200
0#
#204
1#
#205
b1100100 !
b1100100 3
#206
b1101000 4
#208
0#
#212
1#
#213
b1101000 !
b1101000 3
#214
b1101100 4
#216
0#
#220
1#
#221
b1101100 !
b1101100 3
#222
b1110000 4
#224
0#
#228
1#
#229
b1110000 !
b1110000 3
#230
b1110100 4
#232
0#
#236
1#
#237
b1110100 !
b1110100 3
#238
b1111000 4
#240
0#
#244
1#
#245
b1111000 !
b1111000 3
#246
b1111100 4
#248
0#
#252
1#
#253
b1111100 !
b1111100 3
#254
b10000000 4
#256
0#
#260
1#
#261
b10000000 !
b10000000 3
#262
b10000100 4
#264
0#
#268
1#
#269
b10000100 !
b10000100 3
#270
b10001000 4
#272
0#
#276
1#
#277
b10001000 !
b10001000 3
#278
b10001100 4
#280
0#
#284
1#
#285
b10001100 !
b10001100 3
#286
b10010000 4
#288
0#
#292
1#
#293
b10010000 !
b10010000 3
#294
b10010100 4
#296
0#
#300
1#
#301
b10010100 !
b10010100 3
#302
b10011000 4
