Part 1/ALU/or.v

// E19205, E19210
// Group 32

//The OR functional unit performs the logical OR operation on the two 8-bit numbers given in DATA1 and DATA2 and sends the answer to the RESULT output
//Contains a delay of 1 time unit
module OR(DATA1, DATA2, RESULT);

	//Input port declaration
	input [7:0] DATA1, DATA2;
	
	//Declaration of output port
	output [7:0] RESULT;
	
	//Assigns logical OR result of DATA1 and DATA2 to RESULT after 1 time unit delay
	assign #1 RESULT = DATA1 | DATA2;
	
endmodule

Part 1/ALU/and.v

// E19205, E19210
// Group 32

//The AND functional unit performs the logical AND operation on the two 8-bit numbers given in DATA1 and DATA2 and sends the answer to the RESULT output
//Contains a delay of 1 time unit
module AND(DATA1, DATA2, RESULT);

	//Input port declaration
	input [7:0] DATA1, DATA2;
	
	//Declaration of output port
	output [7:0] RESULT;
	
	//Assigns logical AND result of DATA1 and DATA2 to RESULT after 1 time unit delay
	assign #1 RESULT = DATA1 & DATA2;
	
endmodule

Part 1/ALU/add.v

// E19205, E19210
// Group 54


// DATA1 & DATA2 are the inputs.
// Sends the answer to the RESULT 
//Contains a delay of 2 time units
module ADD(DATA1, DATA2, RESULT);

	//Declaration of two 8-bit data inputs
	input [7:0] DATA1, DATA2;
	
	//Declaration of output
	output [7:0] RESULT;
	
	//Assigns evaluated addition of DATA1 and DATA2 to RESULT after 2 time unit delay
	assign #2 RESULT = DATA1 + DATA2;
	
endmodule

Part 1/ALU/forward.v

// E19205, E19210
// Group 32


//The FORWARD functional unit simply forwards the DATA input to the RESULT output
//Contains a delay of 1 time unit
module FORWARD(DATA, RESULT);

	//Input port declaration
	input [7:0] DATA;
	
	//Output port declaration
	output [7:0] RESULT;
	
	//Assigns the value of DATA to RESULT after a delay of 1 time unit
	assign #1 RESULT = DATA;

endmodule

Part 1/ALU/alu.v

// E19205, E19210
// Group 32

// DATA1 & DATA2 are inputs.
// SELECT is the xelector that select the operation to be performed
// RESULT gives the output of the operation

module alu(DATA1, DATA2, RESULT, SELECT);
	
	//Declaration of input ports
	input [7:0] DATA1, DATA2;
	input [2:0] SELECT;
	
	//Output port declaration
	output reg [7:0] RESULT;
	
	//Set of wires to get the outputs of each functional unit
	wire [7:0] forwardOut, addOut, andOut, orOut;
	
	
	// Creating the instances of deferent units
	FORWARD forwardUnit(DATA2, forwardOut);
	ADD addUnit(DATA1, DATA2, addOut);
	AND andUnit(DATA1, DATA2, andOut);
	OR orUnit(DATA1, DATA2, orOut);
	
	
	// Implimentation of the selector MUX
	// The selected functionality output will be desplayed
	always @ (forwardOut, addOut, andOut, orOut, SELECT)	// When the value of the any element is changed, It will be displayed
	begin
		case (SELECT)		//Case statement to switch between the outputs

			3'b000 :	RESULT = forwardOut;	//SELECT = 0 : FORWARD
			
			3'b001 :	RESULT = addOut;		//SELECT = 1 : ADD
			
			3'b010 :	RESULT = andOut;		//SELECT = 2 : AND
			
			3'b011 :	RESULT = orOut;			//SELECT = 3 : OR
			
		endcase
	end

	module AND(DATA1, DATA2, RESULT);

	//Input port declaration
	input [7:0] DATA1, DATA2;
	
	//Declaration of output port
	output [7:0] RESULT;
	
	//Assigns logical AND result of DATA1 and DATA2 to RESULT after 1 time unit delay
	assign #1 RESULT = DATA1 & DATA2;
	
endmodule
		
endmodule

Part 1/ALU/testbench.v
`include "alu.v"

module testbench;

	//Input ports for ALU
	reg [7:0] op1, op2;
	reg [2:0] sel;
	
	//Output port of ALU
	wire [7:0] result;
	
	//Instantiate the ALU
	alu my_alu(op1, op2, result, sel);
	
	//Simulate changes to inputs to test ALU output behaviour
	initial begin
		//Forwarding
		op1 = 5;	
		op2 = 7;
		sel = 0;
		
		#5
		//Add operation
		op2 = 7;
		sel = 1;
		
		

		#5
		//AND operation
		op2 = 12;
		sel = 2;
		
		#5
		//OR operation
		op1 = 10;
		sel = 3;

		
		
	end
	
	//Initial block to monitor changes and dump wavedata to vcd file
	initial begin
		$dumpfile("wavedata.vcd");
		$dumpvars(0, my_alu);
		$monitor("TIME = %g OP1 = %d OP2 = %d SEL = %b RESULT = %d", $time, op1, op2, sel, result);
		#50 $finish;
	end

endmodule

Part 1/ALU/wavedata.vcd
$date
	Wed May 10 10:06:19 2023
$end
$version
	Icarus Verilog
$end
$timescale
	1s
$end
$scope module testbench $end
$scope module my_alu $end
$var wire 8 ! DATA1 [7:0] $end
$var wire 8 " DATA2 [7:0] $end
$var wire 3 # SELECT [2:0] $end
$var wire 8 $ orOut [7:0] $end
$var wire 8 % forwardOut [7:0] $end
$var wire 8 & andOut [7:0] $end
$var wire 8 ' addOut [7:0] $end
$var reg 8 ( RESULT [7:0] $end
$scope module addUnit $end
$var wire 8 ) DATA1 [7:0] $end
$var wire 8 * DATA2 [7:0] $end
$var wire 8 + RESULT [7:0] $end
$upscope $end
$scope module andUnit $end
$var wire 8 , DATA1 [7:0] $end
$var wire 8 - DATA2 [7:0] $end
$var wire 8 . RESULT [7:0] $end
$upscope $end
$scope module forwardUnit $end
$var wire 8 / DATA [7:0] $end
$var wire 8 0 RESULT [7:0] $end
$upscope $end
$scope module orUnit $end
$var wire 8 1 DATA1 [7:0] $end
$var wire 8 2 DATA2 [7:0] $end
$var wire 8 3 RESULT [7:0] $end
$upscope $end
$upscope $end
$upscope $end
$enddefinitions $end
$comment Show the parameter values. $end
$dumpall
$end
#0
$dumpvars
bx 3
b111 2
b101 1
bx 0
b111 /
bx .
b111 -
b101 ,
bx +
b111 *
b101 )
bx (
bx '
bx &
bx %
bx $
b0 #
b111 "
b101 !
$end
#1
b111 (
b111 $
b111 3
b101 &
b101 .
b111 %
b111 0
#2
b1100 '
b1100 +
#5
b1100 (
b1 #
#10
b101 (
b10 #
b1100 "
b1100 *
b1100 -
b1100 /
b1100 2
#11
b100 (
b100 &
b100 .
b1101 $
b1101 3
b1100 %
b1100 0
#12
b10001 '
b10001 +
#15
b1101 (
b11 #
b1010 !
b1010 )
b1010 ,
b1010 1
#16
b1110 (
b1000 &
b1000 .
b1110 $
b1110 3
#17
b10110 '
b10110 +
